{
  "_doc": "2026 NFL Draft results — fantasy-relevant picks (QB/RB/WR/TE) + IDP. Format: {player_name: [pos, college, team, round, overall_pick]}. Source: sharpfootballanalysis.com 2026 draft tracker. Update this file when draft data changes; build_xlsx_v2.py reads from here.",

  "Fernando Mendoza":         ["QB", "Indiana",            "LV",  1, 1],
  "David Bailey":             ["DL", "Stanford",           "NYJ", 1, 2],
  "Jeremiyah Love":           ["RB", "Notre Dame",         "ARI", 1, 3],
  "Carnell Tate":             ["WR", "Ohio State",         "TEN", 1, 4],
  "Arvell Reese":             ["LB", "Ohio State",         "NYG", 1, 5],
  "Mansoor Delane":           ["DB", "LSU",                "KC",  1, 6],
  "Sonny Styles":             ["LB", "Ohio State",         "WAS", 1, 7],
  "Jordyn Tyson":             ["WR", "Arizona State",      "NO",  1, 8],
  "Caleb Downs":              ["DB", "Ohio State",         "DAL", 1, 11],
  "Ty Simpson":               ["QB", "Alabama",            "LAR", 1, 13],
  "Rueben Bain Jr.":          ["DL", "Miami",              "TB",  1, 15],
  "Kenyon Sadiq":             ["TE", "Oregon",             "NYJ", 1, 16],
  "Caleb Banks":              ["DL", "Florida",            "MIN", 1, 18],
  "Makai Lemon":              ["WR", "USC",                "PHI", 1, 20],
  "Akheem Mesidor":           ["DL", "Miami",              "LAC", 1, 22],
  "Malachi Lawrence":         ["DL", "",                   "DAL", 1, 23],
  "KC Concepcion":            ["WR", "Texas A&M",          "CLE", 1, 24],
  "Dillon Thieneman":         ["DB", "Oregon",             "CHI", 1, 25],
  "Chris Johnson":            ["DB", "Penn State",         "MIA", 1, 27],
  "Peter Woods":              ["DL", "Clemson",            "KC",  1, 29],
  "Omar Cooper Jr.":          ["WR", "Indiana",            "NYJ", 1, 30],
  "Keldric Faulk":            ["DL", "Auburn",             "TEN", 1, 31],
  "Jadarian Price":           ["RB", "Notre Dame",         "SEA", 1, 32],

  "De'Zhaun Stribling":       ["WR", "Washington State",   "SF",  2, 33],
  "T.J. Parker":              ["DL", "Clemson",            "BUF", 2, 35],
  "Kayden McDonald":          ["DL", "Ohio State",         "HOU", 2, 36],
  "Colton Hood":              ["DB", "Tennessee",          "NYG", 2, 37],
  "Treydan Stukes":           ["DB", "Arizona",            "LV",  2, 38],
  "Denzel Boston":            ["WR", "Washington",         "CLE", 2, 39],
  "R Mason Thomas":           ["DL", "Oklahoma",           "KC",  2, 40],
  "Cashius Howell":           ["DL", "Texas A&M",          "CIN", 2, 41],
  "Christen Miller":          ["DL", "Georgia",            "NO",  2, 42],
  "Jacob Rodriguez":          ["LB", "Texas Tech",         "MIA", 2, 43],
  "Derrick Moore":            ["DL", "Michigan",           "DET", 2, 44],
  "Zion Young":               ["DL", "Michigan State",     "BAL", 2, 45],
  "Josiah Trotter":           ["LB", "West Virginia",      "TB",  2, 46],
  "Germie Bernard":           ["WR", "Alabama",            "PIT", 2, 47],
  "Avieon Terrell":           ["DB", "Clemson",            "ATL", 2, 48],
  "Lee Hunter":               ["DL", "UCF",                "CAR", 2, 49],
  "D'Angelo Ponds":           ["DB", "Indiana",            "NYJ", 2, 50],
  "Jake Golday":              ["LB", "Stanford",           "MIN", 2, 51],
  "Brandon Cisse":            ["DB", "South Carolina",     "GB",  2, 52],
  "CJ Allen":                 ["LB", "Georgia",            "IND", 2, 53],
  "Eli Stowers":              ["TE", "Vanderbilt",         "PHI", 2, 54],
  "Gabe Jacas":               ["DL", "Illinois",           "NE",  2, 55],
  "Nate Boerkircher":         ["TE", "Nebraska",           "JAX", 2, 56],
  "Emmanuel McNeil-Warren":   ["DB", "Tennessee",          "CLE", 2, 58],
  "Marlin Klein":             ["TE", "Michigan",           "HOU", 2, 59],
  "Anthony Hill Jr.":         ["LB", "Texas",              "TEN", 2, 60],
  "Max Klare":                ["TE", "Ohio State",         "LAR", 2, 61],
  "Davison Igbinosun":        ["DB", "Ohio State",         "BUF", 2, 62],
  "Bud Clark":                ["DB", "TCU",                "SEA", 2, 64],

  "Carson Beck":              ["QB", "Miami",              "ARI", 3, 65],
  "Tyler Onyedim":            ["DL", "Iowa State",         "DEN", 3, 66],
  "Keyron Crawford":          ["DL", "Arkansas State",     "LV",  3, 67],
  "Sam Roush":                ["TE", "Stanford",           "CHI", 3, 69],
  "Romello Height":           ["DL", "Georgia Tech",       "SF",  3, 70],
  "Antonio Williams":         ["WR", "Clemson",            "WAS", 3, 71],
  "Tacario Davis":            ["DB", "Washington",         "CIN", 3, 72],
  "Oscar Delp":               ["TE", "Georgia",            "NO",  3, 73],
  "Malachi Fields":           ["WR", "Virginia",           "NYG", 3, 74],
  "Caleb Douglas":            ["WR", "Florida",            "MIA", 3, 75],
  "Drew Allar":               ["QB", "Penn State",         "PIT", 3, 76],
  "Chris McClellan":          ["DL", "Florida",            "GB",  3, 77],
  "A.J. Haulcy":              ["DB", "LSU",                "IND", 3, 78],
  "Zachariah Branch":         ["WR", "Georgia",            "ATL", 3, 79],
  "Ja'Kobi Lane":             ["WR", "USC",                "BAL", 3, 80],
  "Albert Regis":             ["DL", "Texas A&M",          "JAX", 3, 81],
  "Domonique Orange":         ["DL", "Iowa State",         "MIN", 3, 82],
  "Chris Brazzell II":        ["WR", "Tennessee",          "CAR", 3, 83],
  "Ted Hurst":                ["WR", "Arkansas",           "TB",  3, 84],
  "Daylen Everette":          ["DB", "Georgia",            "PIT", 3, 85],
  "Will Kacmarek":            ["TE", "Ohio State",         "MIA", 3, 87],
  "Zavion Thomas":            ["WR", "LSU",                "CHI", 3, 89],
  "Kaelon Black":              ["RB", "Indiana",           "SF",  3, 90],
  "Jaishawn Barham":          ["LB", "Michigan",           "DAL", 3, 92],
  "Chris Bell":               ["WR", "Louisville",         "MIA", 3, 94],
  "Eli Raridon":              ["TE", "Notre Dame",         "NE",  3, 95],
  "Jakobe Thomas":            ["DB", "Middle Tennessee",   "MIN", 3, 98],
  "Julian Neal":              ["DB", "Fresno State",       "SEA", 3, 99],
  "Jalen Huskey":             ["DB", "Howard",             "JAX", 3, 100],

  "Brenen Thompson":          ["WR", "Mississippi State",  "LAC", 4, 105],
  "Jonah Coleman":            ["RB", "Washington",         "DEN", 4, 108],
  "Cade Klubnik":             ["QB", "Clemson",            "NYJ", 4, 110],
  "Elijah Sarratt":           ["WR", "Indiana",            "BAL", 4, 115],
  "Wesley Williams":          ["DL", "Houston",            "JAX", 4, 119],
  "Dani Dennis-Sutton":       ["DL", "Penn State",         "GB",  4, 120],
  "Kaden Wetjen":             ["WR", "Iowa Western",       "PIT", 4, 121],
  "Mike Washington Jr.":      ["RB", "Arkansas",           "LV",  4, 122],
  "Wade Woodaz":              ["LB", "Clemson",            "HOU", 4, 123],
  "Skyler Bell":              ["WR", "UConn",              "BUF", 4, 125],
  "Kaleb Elarms-Orr":         ["LB", "Cal",                "BUF", 4, 126],
  "Will Lee III":             ["DB", "Kansas State",       "CAR", 4, 129],
  "Trey Moore":               ["DL", "Texas",              "MIA", 4, 130],
  "Genesis Smith":            ["DB", "Auburn",             "LAC", 4, 131],

  "Reggie Virgil":            ["WR", "Miami (OH)",         "ARI", 5, 143],
  "Justin Jefferson":         ["LB", "Tennessee",          "CLE", 5, 149],
  "Justin Joly":              ["TE", "NC State",           "DEN", 5, 152],
  "Jaden Dugger":             ["LB", "Vanderbilt",         "SF",  5, 154],
  "DeMonte Capehart":         ["DL", "Clemson",            "TB",  5, 155],
  "George Gumbs Jr.":         ["DL", "Northern Illinois",  "IND", 5, 156],
  "Keith Abney II":           ["DB", "Maryland",           "DET", 5, 157],
  "Michael Taaffe":           ["DB", "Texas",              "MIA", 5, 158],
  "Max Bredeson":             ["TE", "Michigan",           "MIN", 5, 159],
  "Emmett Johnson":           ["RB", "Nebraska",           "KC",  5, 161],
  "Chandler Rivers":          ["DB", "Duke",               "BAL", 5, 162],
  "Charles Demmings":         ["DB", "UTSA",               "MIN", 5, 163],
  "Tanner Koziol":            ["TE", "Houston",            "JAX", 5, 164],
  "Nicholas Singleton":       ["RB", "Penn State",         "TEN", 5, 165],
  "Keyshaun Elliott":         ["LB", "App State",          "CHI", 5, 166],
  "Jalon Kilgore":            ["DB", "South Carolina",     "BUF", 5, 167],
  "Kendrick Law":             ["WR", "Alabama",            "DET", 5, 168],
  "Riley Nowakowski":         ["TE", "Wisconsin",          "PIT", 5, 169],
  "Joe Royer":                ["TE", "Ohio State",         "CLE", 5, 170],
  "Karon Prunty":             ["DB", "Virginia",           "NE",  5, 171],
  "Lorenzo Styles Jr.":       ["DB", "Notre Dame",         "NO",  5, 172],
  "Josh Cuevas":              ["TE", "Cal Poly",           "BAL", 5, 173],
  "Adam Randall":             ["RB", "Clemson",            "BAL", 5, 174],
  "Hezekiah Masses":          ["DB", "Florida State",      "LV",  5, 175],
  "Cyrus Allen":              ["WR", "Texas Tech",         "KC",  5, 176],
  "Kevin Coleman Jr.":        ["WR", "Mississippi State",  "MIA", 5, 177],
  "Kevin Coleman":            ["WR", "Mississippi State",  "MIA", 5, 177],
  "Cole Payton":              ["QB", "North Dakota State", "PHI", 5, 178],
  "Seydou Traore":            ["TE", "Arkansas State",     "MIA", 5, 180],
  "Zane Durant":              ["DL", "Penn State",         "BUF", 5, 181],

  "Taylen Green":             ["QB", "Arkansas",           "CLE", 6, 182],
  "Karson Sharar":            ["LB", "",                   "ARI", 6, 183],
  "Jackie Marshall":          ["DL", "Arkansas",           "TEN", 6, 184],
  "Bauer Sharp":              ["TE", "Mississippi State",  "TB",  6, 185],
  "Bobby Jamison-Travis":     ["DL", "",                   "NYG", 6, 186],
  "Kaytron Allen":            ["RB", "Penn State",         "WAS", 6, 187],
  "Barion Brown":             ["WR", "Kentucky",           "NO",  6, 190],
  "Josh Cameron":             ["WR", "Notre Dame",         "JAX", 6, 191],
  "Jack Kelly":               ["LB", "Boise State",        "NYG", 6, 193],
  "Malik Benson":             ["WR", "LSU",                "LV",  6, 195],
  "CJ Daniels":               ["WR", "LSU",                "LAR", 6, 197],
  "Demond Claiborne":         ["RB", "Wake Forest",        "MIN", 6, 198],
  "Emmanuel Henderson Jr.":   ["WR", "Alabama",            "SEA", 6, 199],
  "CJ Williams":              ["WR", "USC",                "JAX", 6, 203],
  "Lewis Bond":               ["WR", "Boston College",     "HOU", 6, 204],
  "Skyler Gill-Howard":       ["DL", "Northern Illinois",  "DET", 6, 205],
  "Anterio Thompson":         ["DL", "Western Michigan",   "ATL", 6, 208],
  "Gabriel Rubio":            ["DL", "Stanford",           "PIT", 6, 210],
  "Namdi Obiazor":            ["LB", "Vanderbilt",         "NE",  6, 212],
  "Jordan Van den Berg":      ["DL", "Penn State",         "CHI", 6, 213],
  "Caden Curry":              ["DL", "Ohio State",         "IND", 6, 214],
  "Harold Perkins Jr.":       ["LB", "LSU",                "ATL", 6, 215],

  "Anthony Smith":            ["WR", "",                   "DAL", 7, 218],
  "TJ Hall":                  ["DB", "",                   "NO",  7, 219],
  "Toriano Pride Jr.":        ["DB", "Missouri",           "BUF", 7, 220],
  "Jack Endries":             ["TE", "Texas",              "CIN", 7, 221],
  "Tyre West":                ["DL", "Tennessee",          "DET", 7, 222],
  "Athan Kaliakmanis":        ["QB", "Rutgers",            "WAS", 7, 223],
  "Robert Spears-Jennings":   ["DB", "Oklahoma",           "PIT", 7, 224],
  "Jaren Kanak":              ["TE", "Kansas",             "TEN", 7, 225],
  "Landon Robinson":          ["DL", "",                   "CIN", 7, 226],
  "Jackson Kuwatch":          ["LB", "",                   "CAR", 7, 227],
  "VJ Payne":                 ["DB", "App State",          "NYJ", 7, 228],
  "Brandon Cleveland":        ["DL", "",                   "LV",  7, 229],
  "Eli Heidenreich":          ["RB", "Navy",               "PIT", 7, 230],
  "Tim Keenan III":           ["DL", "Alabama",            "LAR", 7, 232],
  "Zach Durfee":              ["DL", "Sioux Falls",        "JAX", 7, 233],
  "Behren Morton":            ["QB", "Texas Tech",         "NE",  7, 234],
  "Andre Fuller":             ["DB", "",                   "SEA", 7, 236],
  "Seth McGowan":             ["RB", "Oklahoma State",     "IND", 7, 237],
  "Max Llewellyn":            ["DL", "Purdue",             "MIA", 7, 238],
  "Parker Hughes":            ["LB", "",                   "JAX", 7, 240],
  "Deven Eastern":            ["DL", "",                   "SEA", 7, 242],
  "Aiden Fisher":             ["LB", "Indiana",            "HOU", 7, 243],
  "Jam Miller":               ["RB", "Alabama",            "NE",  7, 245],
  "Quintayvious Hutchins":    ["DL", "",                   "NE",  7, 247],
  "Casen Ryan":               ["TE", "BYU",                "CLE", 7, 248],
  "Carsen Ryan":              ["TE", "BYU",                "CLE", 7, 248],
  "Garrett Nussmeier":        ["QB", "LSU",                "KC",  7, 249],
  "Rayshaun Benny":           ["DL", "Michigan",           "BAL", 7, 250],
  "Keyshawn James-Newby":     ["DL", "",                   "PHI", 7, 252],
  "Deion Burks":              ["WR", "Oklahoma",           "IND", 7, 254],
  "Dallen Bentley":           ["TE", "BYU",                "DEN", 7, 256],

  "_undrafted_doc": "Players below were NOT drafted in the 2026 NFL Draft (UDFA, projected fa). Round/pick = null.",
  "Diego Pavia":              ["QB", "Vanderbilt",         "FA",  null, null],
  "Le'Veon Moss":             ["RB", "Texas A&M",          "FA",  null, null],
  "Sawyer Robertson":         ["QB", "Baylor",             "FA",  null, null]
}
